[
  {
    "id": "p1",
    "brandId": "b1",
    "name": "iPhone 15 Pro",
    "price": 93399,
    "storage": "256GB",
    "ram":"8GB",
    "image": "iphone_15_pro.jpg",
    "description": "The ultimate iPhone with titanium design and A17 Pro chip.",
    "floor": 1,
    "mapX": 520,
    "mapY": 295,
    "kioskPaths": {
      "kiosk_floor1_main": "M 400 550 L 400 295 L 520 295",
      "kiosk_floor2_atrium": {
        "lift": {
          "start_floor_segment": "M 399 500 L 401 444 L 213 436 L 209 302",
          "target_floor_segment": "M 209 298 L 209 320 L 401 322 L 399 294 L 519 296"
        },
        "escalator": {
          "start_floor_segment": "M 401 500 L 401 446 L 601 428 L 599 170 L 399 164",
          "target_floor_segment": "M 400 150 V 295 L 520 295"
        },
        "stairs": {
          "start_floor_segment": "M 399 502 V 442 H 607",
          "target_floor_segment": "M 598 448 V 376 H 400 V 293 H 515"
        }
      },
      "kiosk_floor3_foodcourt": {
        "lift": {
          "start_floor_segment": "M 397 500 V 410 H 209 V 298",
          "target_floor_segment": "M 210 299 V 328 H 426 V 297 H 520"
        },
        "escalator": {
          "start_floor_segment": "M 399 499 V 252",
          "target_floor_segment": "M 400 150 V 295 L 520 295"
        },
        "stairs": {
          "start_floor_segment": "M 399 504 V 440 H 609",
          "target_floor_segment": "M 599 450 V 380 H 401 V 296 H 521"
        }
      }
    }
  },
  {
    "id": "p2",
    "brandId": "b1",
    "name": "iPhone 14 Plus",
    "price": 3799,
    "storage": "128GB",
    "ram":"8GB",
    "image": "iphone_14.jpg",
    "description": "Super-sized display and incredibly long battery life.",
    "floor": 1,
    "mapX": 520,
    "mapY": 295,
    "kioskPaths": {
      "kiosk_floor1_main": "M 400 550 L 400 295 L 520 295",
      "kiosk_floor2_atrium": {
        "lift": {
          "start_floor_segment": "M 399 500 L 401 444 L 213 436 L 209 302",
          "target_floor_segment": "M 209 298 L 209 320 L 401 322 L 399 294 L 519 296"
        },
        "escalator": {
          "start_floor_segment": "M 401 500 L 401 446 L 601 428 L 599 170 L 399 164",
          "target_floor_segment": "M 400 150 V 295 L 520 295"
        },
        "stairs": {
          "start_floor_segment": "M 399 502 V 442 H 607",
          "target_floor_segment": "M 598 448 V 376 H 400 V 293 H 515"
        }
      },
      "kiosk_floor3_foodcourt": {
        "lift": {
          "start_floor_segment": "M 397 500 V 410 H 209 V 298",
          "target_floor_segment": "M 210 299 V 328 H 426 V 297 H 520"
        },
        "escalator": {
          "start_floor_segment": "M 399 499 V 252",
          "target_floor_segment": "M 400 150 V 295 L 520 295"
        },
        "stairs": {
          "start_floor_segment": "M 399 504 V 440 H 609",
          "target_floor_segment": "M 599 450 V 380 H 401 V 296 H 521"
        }
      }
    }
  },
  {
    "id": "p4",
    "brandId": "b4",
    "name": "Nothing Phone (3a)",
    "price": 31299,
    "storage": "256GB",
    "ram":"8GB",
    "image": "nothing_3.jpg",
    "description": "Powerfully unique. Stunning performance.",
    "floor": 1,
    "mapX": 110,
    "mapY": 190,
    "kioskPaths": {
      "kiosk_floor1_main": "M 399 550 L 395 178 L 201 180 L 197 194 L 109 196",
      "kiosk_floor2_atrium": {
        "lift": {
          "start_floor_segment": "M 397 498 L 397 446 L 209 426 L 209 302",
          "target_floor_segment": "M 209 298 L 207 196 L 109 194"
        },
        "escalator": {
          "start_floor_segment": "M 401 496 L 401 444 L 599 440 L 579 172 L 399 166",
          "target_floor_segment": "M 397 150 L 401 174 L 195 176 L 195 208 L 111 196"
        },
        "stairs": {
          "start_floor_segment": "M 399 502 V 442 H 607",
          "target_floor_segment": "M 597 444 L 599 376 L 399 376 L 395 182 L 199 176 L 197 198 L 111 194"
        }
      },
      "kiosk_floor3_foodcourt": {
        "lift": {
          "start_floor_segment": "M 397 500 V 410 H 209 V 298",
          "target_floor_segment": "M 209 296 L 207 200 L 111 196"
        },
        "escalator": {
          "start_floor_segment": "M 399 499 V 252",
          "target_floor_segment": "M 401 150 L 399 180 L 193 182 L 193 192 L 115 190"
        },
        "stairs": {
          "start_floor_segment": "M 399 504 V 440 H 609",
          "target_floor_segment": "M 597 444 L 599 376 L 399 376 L 395 182 L 199 176 L 197 198 L 111 194"
        }
      }
    }
  },
  {
    "id": "p5",
    "brandId": "b5",
    "name": "Nike Store",
    "price": null,
    "storage": "",
    "image": "Nike2.jpg",
    "description": "Just Do It. Premium athletic footwear, apparel, and sports accessories.",
    "floor": 2,
    "mapX": 677,
    "mapY": 115,
    "kioskPaths": {
      "kiosk_floor1_main": {
        "lift": {
          "start_floor_segment": "M 401 552 V 320 H 205 V 300",
          "target_floor_segment": "M 209 302 L 211 434 L 605 430 L 605 172 L 677 168 L 677 118"
        },
        "escalator": {
          "start_floor_segment": "M 400 550 V 150",
          "target_floor_segment": "M 397 164 L 677 168 L 675 114"
        },
        "stairs": {
          "start_floor_segment": "M 400 550 H 600 V 450",
          "target_floor_segment": "M 607 444 L 607 172 L 677 168 L 679 116"
        }
      },
      "kiosk_floor2_atrium": "M 393 504 L 387 444 L 605 442 L 609 174 L 677 170 L 679 120",
      "kiosk_floor3_foodcourt": {
        "lift": {
          "start_floor_segment": "M 401 502 L 401 502 L 401 502 L 391 320 L 207 314 L 207 300",
          "target_floor_segment": "M 209 302 L 211 434 L 605 430 L 605 172 L 677 168 L 677 118"
        },
        "escalator": {
          "start_floor_segment": "M 399 502 L 397 250",
          "target_floor_segment": "M 397 164 L 677 168 L 675 114"
        },
        "stairs": {
          "start_floor_segment": "M 399 500 L 395 444 L 609 442",
          "target_floor_segment": "M 607 444 L 607 172 L 677 168 L 679 116"
        }
      }
    }
  },
  {
    "id": "p6",
    "brandId": "b2",
    "name": "Samsung Galaxy S24 Ultra",
    "price": 129999,
    "storage": "512GB",
    "image": "samsung-1.jpg",
    "description": "Galaxy AI is here. Welcome to the era of mobile AI.",
    "floor": 1,
    "mapX": 110,
    "mapY": 195,
    "kioskPaths": {
      "kiosk_floor1_main": "M 399 550 L 395 178 L 201 180 L 197 194 L 109 196",
      "kiosk_floor2_atrium": {
        "lift": {
          "start_floor_segment": "M 397 498 L 397 446 L 209 426 L 209 302",
          "target_floor_segment": "M 209 298 L 207 196 L 109 194"
        },
        "escalator": {
          "start_floor_segment": "M 401 496 L 401 444 L 599 440 L 579 172 L 399 166",
          "target_floor_segment": "M 397 150 L 401 174 L 195 176 L 195 208 L 111 196"
        },
        "stairs": {
          "start_floor_segment": "M 399 502 V 442 H 607",
          "target_floor_segment": "M 597 444 L 599 376 L 399 376 L 395 182 L 199 176 L 197 198 L 111 194"
        }
      },
      "kiosk_floor3_foodcourt": {
        "lift": {
          "start_floor_segment": "M 397 500 V 410 H 209 V 298",
          "target_floor_segment": "M 209 296 L 207 200 L 111 196"
        },
        "escalator": {
          "start_floor_segment": "M 399 499 V 252",
          "target_floor_segment": "M 401 150 L 399 180 L 193 182 L 193 192 L 115 190"
        },
        "stairs": {
          "start_floor_segment": "M 399 504 V 440 H 609",
          "target_floor_segment": "M 597 444 L 599 376 L 399 376 L 395 182 L 199 176 L 197 198 L 111 194"
        }
      }
    }
  },
  {
    "id": "p7",
    "brandId": "b3",
    "name": "OnePlus 12",
    "price": 64999,
    "storage": "256GB",
    "image": "oneplus-1.jpg",
    "description": "Smooth Beyond Belief. Experience the new Hasselblad Camera.",
    "floor": 1,
    "mapX": 110,
    "mapY": 295,
    "kioskPaths": {
      "kiosk_floor1_main": "M 399 548 L 391 466 L 195 460 L 183 300 L 107 292",
      "kiosk_floor2_atrium": {
        "lift": {
          "start_floor_segment": "M 399 500 L 401 444 L 213 436 L 209 302",
          "target_floor_segment": "M 211 298 L 109 296"
        },
        "escalator": {
          "start_floor_segment": "M 401 500 L 401 446 L 601 428 L 599 170 L 399 164",
          "target_floor_segment": "M 401 148 L 395 312 L 203 318 L 203 288 L 109 294"
        },
        "stairs": {
          "start_floor_segment": "M 399 502 V 442 H 607",
          "target_floor_segment": "M 599 446 V 378 H 397 V 320 H 201 V 296 H 113"
        }
      },
      "kiosk_floor3_foodcourt": {
        "lift": {
          "start_floor_segment": "M 397 500 V 410 H 209 V 298",
          "target_floor_segment": "M 211 298 L 109 296"
        },
        "escalator": {
          "start_floor_segment": "M 399 499 V 252",
          "target_floor_segment": "M 401 148 L 395 312 L 203 318 L 203 288 L 109 294"
        },
        "stairs": {
          "start_floor_segment": "M 399 504 V 440 H 609",
          "target_floor_segment": "M 599 446 V 378 H 397 V 320 H 201 V 296 H 113"
        }
      }
    }
  },
  {
    "id": "p8",
    "brandId": "b6",
    "name": "UCB Retail Store",
    "price": null,
    "storage": "",
    "image": "UCB.jpg",
    "description": "United Colors of Benetton fashion apparel and accessories.",
    "floor": 2,
    "mapX": 115,
    "mapY": 240,
    "kioskPaths": {
      "kiosk_floor1_main": {
        "lift": {
          "start_floor_segment": "M 401 552 V 320 H 205 V 300",
          "target_floor_segment": "M 207 296 L 209 242 L 113 240"
        },
        "escalator": {
          "start_floor_segment": "M 400 550 V 150",
          "target_floor_segment": "M 399 164 L 197 168 L 197 244 L 113 240"
        },
        "stairs": {
          "start_floor_segment": "M 400 550 H 600 V 450",
          "target_floor_segment": "M 600 450 H 200 V 243 H 114"
        }
      },
      "kiosk_floor2_atrium": "M 397 506 L 397 440 L 201 434 L 199 244 L 117 242",
      "kiosk_floor3_foodcourt": {
        "lift": {
          "start_floor_segment": "M 401 502 L 401 502 L 401 502 L 391 320 L 207 314 L 207 300",
          "target_floor_segment": "M 207 296 L 209 242 L 113 240"
        },
        "escalator": {
          "start_floor_segment": "M 399 502 L 397 250",
          "target_floor_segment": "M 399 164 L 197 168 L 197 244 L 113 240"
        },
        "stairs": {
          "start_floor_segment": "M 399 500 L 395 444 L 609 442",
          "target_floor_segment": "M 600 450 H 200 V 243 H 114"
        }
      }
    }
  },
  {
    "id": "p9",
    "brandId": "b7",
    "name": "Adidas Originals",
    "price": null,
    "storage": "",
    "image": "Adidas.jpg",
    "description": "Impossible is Nothing. Premium sports and streetwear.",
    "floor": 2,
    "mapX": 115,
    "mapY": 380,
    "kioskPaths": {
      "kiosk_floor1_main": {
        "lift": {
          "start_floor_segment": "M 401 552 V 320 H 205 V 300",
          "target_floor_segment": "M 207 300 L 209 380 L 115 380"
        },
        "escalator": {
          "start_floor_segment": "M 400 550 V 150",
          "target_floor_segment": "M 399 164 L 201 170 L 191 376 L 113 374"
        },
        "stairs": {
          "start_floor_segment": "M 400 550 H 600 V 450",
          "target_floor_segment": "M 605 444 L 199 444 L 199 376 L 113 376"
        }
      },
      "kiosk_floor2_atrium": "M 395 512 L 391 446 L 199 444 L 199 378 L 111 378",
      "kiosk_floor3_foodcourt": {
        "lift": {
          "start_floor_segment": "M 401 502 L 401 502 L 401 502 L 391 320 L 207 314 L 207 300",
          "target_floor_segment": "M 207 300 L 209 380 L 115 380"
        },
        "escalator": {
          "start_floor_segment": "M 399 502 L 397 250",
          "target_floor_segment": "M 399 164 L 201 170 L 191 376 L 113 374"
        },
        "stairs": {
          "start_floor_segment": "M 399 500 L 395 444 L 609 442",
          "target_floor_segment": "M 605 444 L 199 444 L 199 376 L 113 376"
        }
      }
    }
  },
  {
    "id": "p10",
    "brandId": "b8",
    "name": "Puma Outlet",
    "price": null,
    "storage": "",
    "image": "Puma.jpg",
    "description": "Forever Faster. Shop activewear and lifestyle products.",
    "floor": 3,
    "mapX": 115,
    "mapY": 250,
    "kioskPaths": {
      "kiosk_floor1_main": {
        "lift": {
          "start_floor_segment": "M 401 552 V 320 H 205 V 300",
          "target_floor_segment": "M 207 300 L 209 248 L 111 246"
        },
        "escalator": {
          "start_floor_segment": "M 400 550 V 150",
          "target_floor_segment": "M 399 250 L 113 246"
        },
        "stairs": {
          "start_floor_segment": "M 400 550 H 600 V 450",
          "target_floor_segment": "M 600 450 V 250 H 115"
        }
      },
      "kiosk_floor2_atrium": {
        "lift": {
          "start_floor_segment": "M 399 500 L 401 444 L 213 436 L 209 302",
          "target_floor_segment": "M 209 300 L 209 248 L 109 248"
        },
        "escalator": {
          "start_floor_segment": "M 401 500 L 401 446 L 601 428 L 599 170 L 399 164",
          "target_floor_segment": "M 401 250 L 113 246"
        },
        "stairs": {
          "start_floor_segment": "M 399 502 V 442 H 607",
          "target_floor_segment": "M 600 450 V 250 H 115"
        }
      },
      
      "kiosk_floor3_foodcourt": "M 400 500 V 250 H 115"
    }
  },
  {
    "id": "p11",
    "brandId": "b9",
    "name": "Air Jordan",
    "price": null,
    "storage": "",
    "image": "Jordan.jpg",
    "description": "Defy the rules. Explore iconic sneakers and apparel.",
    "floor": 3,
    "mapX": 685,
    "mapY": 250,
    "kioskPaths": {
      "kiosk_floor1_main": {
        "lift": {
          "start_floor_segment": "M 401 552 V 320 H 205 V 300",
          "target_floor_segment": "M 209 298 L 211 298 L 207 250 L 683 250"
        },
        "escalator": {
          "start_floor_segment": "M 400 550 V 150",
          "target_floor_segment": "M 399 248 L 681 250"
        },
        "stairs": {
          "start_floor_segment": "M 400 550 H 600 V 450",
          "target_floor_segment": "M 607 442 L 607 250 L 683 248"
        }
      },
      "kiosk_floor2_atrium": {
        "lift": {
          "start_floor_segment": "M 399 500 L 401 444 L 213 436 L 209 302",
          "target_floor_segment": "M 209 298 L 211 298 L 207 250 L 683 250"
        },
        "escalator": {
          "start_floor_segment": "M 401 500 L 401 446 L 601 428 L 599 170 L 399 164",
          "target_floor_segment": "M 399 248 L 681 250"
        },
        "stairs": {
          "start_floor_segment": "M 399 502 V 442 H 607",
          "target_floor_segment": "M 607 442 L 607 250 L 683 248"
        }
      },
      "kiosk_floor3_foodcourt": "M 400 500 V 255 H 685"
    }
  },
  {
    "id": "p12",
    "brandId": "b10",
    "name": "Decathlon",
    "price": null,
    "storage": "",
    "image": "Decathalon.jpg",
    "description": "Sport for all. All for sport. Find gear for 70+ sports.",
    "floor": 3,
    "mapX": 685,
    "mapY": 395,
    "kioskPaths": {
      "kiosk_floor1_main": {
        "lift": {
          "start_floor_segment": "M 401 552 V 320 H 205 V 300",
          "target_floor_segment": "M 209 298 L 211 390 L 683 396"
        },
        "escalator": {
          "start_floor_segment": "M 400 550 V 150",
          "target_floor_segment": "M 399 252 L 409 390 L 683 394"
        },
        "stairs": {
          "start_floor_segment": "M 400 550 H 600 V 450",
          "target_floor_segment": "M 607 442 L 605 390 L 687 394"
        }
      },
      "kiosk_floor2_atrium": {
        "lift": {
          "start_floor_segment": "M 399 500 L 401 444 L 213 436 L 209 302",
          "target_floor_segment": "M 209 298 L 211 390 L 683 396"
        },
        "escalator": {
          "start_floor_segment": "M 401 500 L 401 446 L 601 428 L 599 170 L 399 164",
          "target_floor_segment": "M 399 252 L 409 390 L 683 394"
        },
        "stairs": {
          "start_floor_segment": "M 399 502 V 442 H 607",
          "target_floor_segment": "M 607 442 L 605 390 L 687 394"
        }
      },
      "kiosk_floor3_foodcourt": "M 400 500 V 402 H 685"
    }
  },
  {
    "id": "p13",
    "brandId": "b11",
    "name": "Tanishq Jewellers",
    "price": null,
    "storage": "",
    "image": "Tanishq.jpg",
    "description": "A Tata Product. Exquisite gold and diamond jewellery.",
    "floor": 1,
    "mapX": 105,
    "mapY": 485,
    "kioskPaths": {
      "kiosk_floor1_main": "M 400 550 L 400 460 L 210 460 L 210 485 L 105 485",
      "kiosk_floor2_atrium": {
        "lift": {
          "start_floor_segment": "M 399 500 L 401 444 L 213 436 L 209 302",
          "target_floor_segment": "M 209 300 L 201 482 L 103 486"
        },
        "escalator": {
          "start_floor_segment": "M 401 500 L 401 446 L 601 428 L 599 170 L 399 164",
          "target_floor_segment": "M 397 150 L 389 466 L 183 474 L 183 488 L 105 486"
        },
        "stairs": {
          "start_floor_segment": "M 399 502 V 442 H 607",
          "target_floor_segment": "M 599 448 L 597 494 L 437 496 L 435 466 L 195 468 L 195 492 L 105 488"
        }
      },
      "kiosk_floor3_foodcourt": {
        "lift": {
          "start_floor_segment": "M 397 500 V 410 H 209 V 298",
          "target_floor_segment": "M 209 300 L 201 482 L 103 486"
        },
        "escalator": {
          "start_floor_segment": "M 399 499 V 252",
          "target_floor_segment": "M 397 150 L 389 466 L 183 474 L 183 488 L 105 486"
        },
        "stairs": {
          "start_floor_segment": "M 399 504 V 440 H 609",
          "target_floor_segment": "M 599 448 L 597 494 L 437 496 L 435 466 L 195 468 L 195 492 L 105 488"
        }
      }
    }
  },
  {
    "id": "p14",
    "brandId": "b12",
    "name": "Bella Vita Luxury",
    "price": null,
    "storage": "",
    "image": "Bellavita.jpg",
    "description": "Premium luxury perfumes and personal care products.",
    "floor": 1,
    "mapX": 310,
    "mapY": 115,
    "kioskPaths": {
      "kiosk_floor1_main": "M 400 550 L 400 150 L 310 150 L 310 115",
      "kiosk_floor2_atrium": {
        "lift": {
          "start_floor_segment": "M 399 500 L 401 444 L 213 436 L 209 302",
          "target_floor_segment": "M 209 298 L 209 110 L 311 116"
        },
        "escalator": {
          "start_floor_segment": "M 401 500 L 401 446 L 601 428 L 599 170 L 399 164",
          "target_floor_segment": "M 401 150 L 399 118 L 309 116"
        },
        "stairs": {
          "start_floor_segment": "M 399 502 V 442 H 607",
          "target_floor_segment": "M 601 448 L 597 378 L 397 378 L 389 118 L 311 116"
        }
      },
      "kiosk_floor3_foodcourt": {
        "lift": {
          "start_floor_segment": "M 397 500 V 410 H 209 V 298",
          "target_floor_segment": "M 209 298 L 209 110 L 311 116"
        },
        "escalator": {
          "start_floor_segment": "M 399 499 V 252",
          "target_floor_segment": "M 401 150 L 399 118 L 309 116"
        },
        "stairs": {
          "start_floor_segment": "M 399 504 V 440 H 609",
          "target_floor_segment": "M 601 448 L 597 378 L 397 378 L 389 118 L 311 116"
        }
      }
    }
  },
  {
    "id": "p15",
    "brandId": "b13",
    "name": "Apollo Pharmacy",
    "price": null,
    "storage": "",
    "image": "appolo.jpg",
    "description": "Your trusted local pharmacy for medicines and healthcare.",
    "floor": 3,
    "mapX": 552,
    "mapY": 510,
    "kioskPaths": {
      "kiosk_floor1_main": {
        "lift": {
          "start_floor_segment": "M 401 552 V 320 H 205 V 300",
          "target_floor_segment": "M 209 302 L 211 390 L 543 392 L 549 510"
        },
        "escalator": {
          "start_floor_segment": "M 400 550 V 150",
          "target_floor_segment": "M 401 252 L 399 388 L 555 388 L 549 510"
        },
        "stairs": {
          "start_floor_segment": "M 400 550 H 600 V 450",
          "target_floor_segment": "M 607 444 L 603 410 L 555 406 L 553 506"
        }
      },
      "kiosk_floor2_atrium": {
        "lift": {
          "start_floor_segment": "M 399 500 L 401 444 L 213 436 L 209 302",
          "target_floor_segment": "M 209 302 L 211 390 L 543 392 L 549 510"
        },
        "escalator": {
          "start_floor_segment": "M 401 500 L 401 446 L 601 428 L 599 170 L 399 164",
          "target_floor_segment": "M 401 252 L 399 388 L 555 388 L 549 510"
        },
        "stairs": {
          "start_floor_segment": "M 399 502 V 442 H 607",
          "target_floor_segment": "M 607 444 L 603 410 L 555 406 L 553 506"
        }
      },
      "kiosk_floor3_foodcourt": "M 399 496 L 401 426 L 551 426 L 549 510"
    }
  },
  {
    "id": "p16",
    "brandId": "b14",
    "name": "KFC",
    "price": null,
    "storage": "",
    "image": "kfc.jpg",
    "description": "Finger Lickin' Good. Original recipe fried chicken.",
    "floor": 3,
    "mapX": 110,
    "mapY": 120,
    "kioskPaths": {
      "kiosk_floor1_main": {
        "lift": {
          "start_floor_segment": "M 401 552 V 320 H 205 V 300",
          "target_floor_segment": "M 207 300 L 207 186 L 109 182 L 107 122"
        },
        "escalator": {
          "start_floor_segment": "M 400 550 V 150",
          "target_floor_segment": "M 399 252 L 195 240 L 191 182 L 107 178 L 109 120"
        },
        "stairs": {
          "start_floor_segment": "M 400 550 H 600 V 450",
          "target_floor_segment": "M 609 442 L 597 246 L 201 238 L 195 186 L 105 178 L 107 118"
        }
      },
      "kiosk_floor2_atrium": {
        "lift": {
          "start_floor_segment": "M 399 500 L 401 444 L 213 436 L 209 302",
          "target_floor_segment": "M 207 300 L 207 186 L 109 182 L 107 122"
        },
        "escalator": {
          "start_floor_segment": "M 401 500 L 401 446 L 601 428 L 599 170 L 399 164",
          "target_floor_segment": "M 399 252 L 195 240 L 191 182 L 107 178 L 109 120"
        },
        "stairs": {
          "start_floor_segment": "M 399 502 V 442 H 607",
          "target_floor_segment": "M 609 442 L 597 246 L 201 238 L 195 186 L 105 178 L 107 118"
        }
      },
      "kiosk_floor3_foodcourt": "M 403 502 L 395 242 L 207 236 L 207 192 L 107 180 L 109 120"
    }
  },
  {
    "id": "p17",
    "brandId": "b15",
    "name": "McDonald's",
    "price": null,
    "storage": "",
    "image": "mcd.jpg",
    "description": "I'm Lovin' It. Burgers, fries, and happy meals.",
    "floor": 3,
    "mapX": 248,
    "mapY": 122,
    "kioskPaths": {
      "kiosk_floor1_main": {
        "lift": {
          "start_floor_segment": "M 401 552 V 320 H 205 V 300",
          "target_floor_segment": "M 209 298 L 211 192 L 249 190 L 249 122"
        },
        "escalator": {
          "start_floor_segment": "M 400 550 V 150",
          "target_floor_segment": "M 399 250 L 277 238 L 275 182 L 251 182 L 249 124"
        },
        "stairs": {
          "start_floor_segment": "M 400 550 H 600 V 450",
          "target_floor_segment": "M 605 442 L 597 242 L 285 236 L 283 182 L 249 180 L 249 122"
        }
      },
      "kiosk_floor2_atrium": {
        "lift": {
          "start_floor_segment": "M 399 500 L 401 444 L 213 436 L 209 302",
          "target_floor_segment": "M 209 298 L 211 192 L 249 190 L 249 122"
        },
        "escalator": {
          "start_floor_segment": "M 401 500 L 401 446 L 601 428 L 599 170 L 399 164",
          "target_floor_segment": "M 399 250 L 277 238 L 275 182 L 251 182 L 249 124"
        },
        "stairs": {
          "start_floor_segment": "M 399 502 V 442 H 607",
          "target_floor_segment": "M 605 442 L 597 242 L 285 236 L 283 182 L 249 180 L 249 122"
        }
      },
      "kiosk_floor3_foodcourt": "M 399 498 L 399 238 L 285 234 L 283 182 L 247 182 L 247 128"
    }
  },
  {
    "id": "p18",
    "brandId": "b16",
    "name": "Pizza Hut",
    "price": null,
    "storage": "",
    "image": "pizzahut.jpg",
    "description": "Make it great. Delicious pan pizzas and sides.",
    "floor": 3,
    "mapX": 692,
    "mapY": 120,
    "kioskPaths": {
      "kiosk_floor1_main": {
        "lift": {
          "start_floor_segment": "M 401 552 V 320 H 205 V 300",
          "target_floor_segment": "M 207 298 L 205 254 L 605 254 L 601 186 L 685 182 L 689 124"
        },
        "escalator": {
          "start_floor_segment": "M 400 550 V 150",
          "target_floor_segment": "M 397 252 L 593 254 L 593 192 L 689 184 L 687 116"
        },
        "stairs": {
          "start_floor_segment": "M 400 550 H 600 V 450",
          "target_floor_segment": "M 607 446 L 605 182 L 687 178 L 687 178 L 689 124"
        }
      },
      "kiosk_floor2_atrium": {
        "lift": {
          "start_floor_segment": "M 399 500 L 401 444 L 213 436 L 209 302",
          "target_floor_segment": "M 207 298 L 205 254 L 605 254 L 601 186 L 685 182 L 689 124"
        },
        "escalator": {
          "start_floor_segment": "M 401 500 L 401 446 L 601 428 L 599 170 L 399 164",
          "target_floor_segment": "M 397 252 L 593 254 L 593 192 L 689 184 L 687 116"
        },
        "stairs": {
          "start_floor_segment": "M 399 502 V 442 H 607",
          "target_floor_segment": "M 607 446 L 605 182 L 687 178 L 687 178 L 689 124"
        }
      },
      "kiosk_floor3_foodcourt": "M 399 502 L 405 240 L 607 240 L 605 188 L 685 182 L 691 126"
    }
  },
  {
    "id": "p19",
    "brandId": "b17",
    "name": "Domino's Pizza",
    "price": null,
    "storage": "",
    "image": "dominos.jpg",
    "description": "Hot and fresh pizza delivered or for dine-in.",
    "floor": 3,
    "mapX": 549,
    "mapY": 123,
    "kioskPaths": {
      "kiosk_floor1_main": {
        "lift": {
          "start_floor_segment": "M 401 552 V 320 H 205 V 300",
          "target_floor_segment": "M 209 296 L 209 244 L 529 240 L 529 186 L 547 186 L 547 122"
        },
        "escalator": {
          "start_floor_segment": "M 400 550 V 150",
          "target_floor_segment": "M 399 249 L 518 249 L 518 187 L 548 184 L 550 123"
        },
        "stairs": {
          "start_floor_segment": "M 400 550 H 600 V 450",
          "target_floor_segment": "M 605 444 L 603 194 L 547 188 L 545 124"
        }
      },
      "kiosk_floor2_atrium": {
        "lift": {
          "start_floor_segment": "M 399 500 L 401 444 L 213 436 L 209 302",
          "target_floor_segment": "M 209 296 L 209 244 L 529 240 L 529 186 L 547 186 L 547 122"
        },
        "escalator": {
          "start_floor_segment": "M 401 500 L 401 446 L 601 428 L 599 170 L 399 164",
          "target_floor_segment": "M 399 249 L 518 249 L 518 187 L 548 184 L 550 123"
        },
        "stairs": {
          "start_floor_segment": "M 399 502 V 442 H 607",
          "target_floor_segment": "M 605 444 L 603 194 L 547 188 L 545 124"
        }
      },
      "kiosk_floor3_foodcourt": "M 395 500 L 407 236 L 521 236 L 521 186 L 549 186 L 549 124"
    }
  }
]